pyscheduler/__init__.py
pyscheduler/helper.py
pyscheduler/scheduler.py
pyscheduler/schedulesearch.py
pyscheduler/data/schedule.json
pyplayscheduler-0.1.dist-info/LICENSE
pyplayscheduler-0.1.dist-info/METADATA
pyplayscheduler-0.1.dist-info/WHEEL
pyplayscheduler-0.1.dist-info/top_level.txt
pyplayscheduler-0.1.dist-info/RECORD
