Metadata-Version: 2.1
Name: pyplayscheduler
Version: 0.1
Summary: python library and webapp for scheduling pickleball games
Author: Eric Truett
Author-email: sansbacon@gmail.com
License: MIT
Classifier: Programming Language :: Python :: 3
Classifier: License :: OSI Approved :: MIT License
Classifier: Operating System :: OS Independent
Requires-Python: >=3.8
License-File: LICENSE
